gdump/__init__.py
gdump/__main__.py
gdump/_assets.py
gdump/_metadata.py
gdump/py.typed
gdump/resources/.gitkeep
gdump-0.1.0.dist-info/LICENSE
gdump-0.1.0.dist-info/METADATA
gdump-0.1.0.dist-info/WHEEL
gdump-0.1.0.dist-info/entry_points.txt
gdump-0.1.0.dist-info/RECORD
