Metadata-Version: 2.1
Name: gdump
Version: 0.1.0
Summary: 📆 Genesis Dumper lets you dump your schedule from Genesis and turn it into an .ICS file for use in Google Calendar or Outlook
Home-page: https://github.com/regulad/gdump
License: GPL-3.0
Author: Parker Wahle
Author-email: regulad@regulad.xyz
Requires-Python: >=3.11,<3.13
Classifier: Development Status :: 1 - Planning
Classifier: License :: OSI Approved :: GNU General Public License v3 (GPLv3)
Classifier: Programming Language :: Python :: 3
Classifier: Programming Language :: Python :: 3.11
Classifier: Programming Language :: Python :: 3.12
Requires-Dist: beautifulsoup4 (>=4.12.3,<5.0.0)
Requires-Dist: ics (>=0.7.2,<0.8.0)
Requires-Dist: importlib-metadata (>=6.8.0,<7.0.0)
Requires-Dist: pytz (>=2024.1,<2025.0)
Requires-Dist: requests (>=2.32.3,<3.0.0)
Requires-Dist: rich (>=13.7.1,<14.0.0)
Requires-Dist: typer[all] (>=0.9.0,<0.10.0)
Requires-Dist: typing-extensions (>=4.7.1,<5.0.0)
Project-URL: Changelog, https://github.com/regulad/gdump/releases
Project-URL: Documentation, https://gdump.readthedocs.io
Project-URL: Repository, https://github.com/regulad/gdump
